milc/__init__.py
milc/_in_argv.py
milc/_sparkline.py
milc/ansi.py
milc/attrdict.py
milc/configuration.py
milc/emoji.py
milc/milc.py
milc/milc_interface.py
milc/questions.py
milc/subcommand/__init__.py
milc/subcommand/config.py
milc-1.9.1.data/scripts/milc-color
milc-1.9.1.dist-info/LICENSE
milc-1.9.1.dist-info/METADATA
milc-1.9.1.dist-info/WHEEL
milc-1.9.1.dist-info/top_level.txt
milc-1.9.1.dist-info/RECORD
